Workbook

Sheet สรุป
B2: FinanceCare — สรุปผลการทดสอบ
B3: ตัวเลขทั้งหมดคำนวณจากชีต Test Cases (คอลัมน์ สถานะ) อัปเดตเองเมื่อแก้สถานะ
B5: ภาพรวมตามสถานะ
B6: สถานะ | C6: จำนวน | D6: สัดส่วน
B7: ยังไม่ทดสอบ | C7: =COUNTIF('Test Cases'!$I$2:$I$300,B7) -> 21 | D7: =IF($C$12=0,0,C7/$C$12) -> 0.18421053
B8: ผ่าน | C8: =COUNTIF('Test Cases'!$I$2:$I$300,B8) -> 91 | D8: =IF($C$12=0,0,C8/$C$12) -> 0.79824561
B9: ไม่ผ่าน | C9: =COUNTIF('Test Cases'!$I$2:$I$300,B9) -> 1 | D9: =IF($C$12=0,0,C9/$C$12) -> 0.0087719298
B10: ข้าม | C10: =COUNTIF('Test Cases'!$I$2:$I$300,B10) -> 1 | D10: =IF($C$12=0,0,C10/$C$12) -> 0.0087719298
B11: บล็อก | C11: =COUNTIF('Test Cases'!$I$2:$I$300,B11) -> 0 | D11: =IF($C$12=0,0,C11/$C$12) -> 0
B12: รวมทั้งหมด | C12: =SUM(C7:C11) -> 114 | D12: =SUM(D7:D11) -> 1
B13: ความคืบหน้า (ผ่าน ÷ รวม) | C13: =IF(C12=0,0,C8/C12) -> 0.79824561
B15: แยกตามกลุ่ม
B16: กลุ่ม | C16: รวม | D16: ผ่าน | E16: ไม่ผ่าน | F16: ข้าม | G16: บล็อก | H16: ยังไม่ทดสอบ | I16: % ผ่าน
B17: หน้า Login (UI อัตโนมัติ) | C17: =COUNTIF('Test Cases'!$B$2:$B$300,B17) -> 10 | D17: =COUNTIFS('Test Cases'!$B$2:$B$300,$B17,'Test Cases'!$I$2:$I$300,"ผ่าน") -> 10 | E17: =COUNTIFS('Test Cases'!$B$2:$B$300,$B17,'Test Cases'!$I$2:$I$300,"ไม่ผ่าน") -> 0 | F17: =COUNTIFS('Test Cases'!$B$2:$B$300,$B17,'Test Cases'!$I$2:$I$300,"ข้าม") -> 0 | G17: =COUNTIFS('Test Cases'!$B$2:$B$300,$B17,'Test Cases'!$I$2:$I$300,"บล็อก") -> 0 | H17: =COUNTIFS('Test Cases'!$B$2:$B$300,$B17,'Test Cases'!$I$2:$I$300,"ยังไม่ทดสอบ") -> 0 | I17: =IF(C17=0,0,D17/C17) -> 1
B18: ปุ่ม Google (อัตโนมัติ) | C18: =COUNTIF('Test Cases'!$B$2:$B$300,B18) -> 2 | D18: =COUNTIFS('Test Cases'!$B$2:$B$300,$B18,'Test Cases'!$I$2:$I$300,"ผ่าน") -> 2 | E18: =COUNTIFS('Test Cases'!$B$2:$B$300,$B18,'Test Cases'!$I$2:$I$300,"ไม่ผ่าน") -> 0 | F18: =COUNTIFS('Test Cases'!$B$2:$B$300,$B18,'Test Cases'!$I$2:$I$300,"ข้าม") -> 0 | G18: =COUNTIFS('Test Cases'!$B$2:$B$300,$B18,'Test Cases'!$I$2:$I$300,"บล็อก") -> 0 | H18: =COUNTIFS('Test Cases'!$B$2:$B$300,$B18,'Test Cases'!$I$2:$I$300,"ยังไม่ทดสอบ") -> 0 | I18: =IF(C18=0,0,D18/C18) -> 1
B19: Backend API (อัตโนมัติ) | C19: =COUNTIF('Test Cases'!$B$2:$B$300,B19) -> 16 | D19: =COUNTIFS('Test Cases'!$B$2:$B$300,$B19,'Test Cases'!$I$2:$I$300,"ผ่าน") -> 16 | E19: =COUNTIFS('Test Cases'!$B$2:$B$300,$B19,'Test Cases'!$I$2:$I$300,"ไม่ผ่าน") -> 0 | F19: =COUNTIFS('Test Cases'!$B$2:$B$300,$B19,'Test Cases'!$I$2:$I$300,"ข้าม") -> 0 | G19: =COUNTIFS('Test Cases'!$B$2:$B$300,$B19,'Test Cases'!$I$2:$I$300,"บล็อก") -> 0 | H19: =COUNTIFS('Test Cases'!$B$2:$B$300,$B19,'Test Cases'!$I$2:$I$300,"ยังไม่ทดสอบ") -> 0 | I19: =IF(C19=0,0,D19/C19) -> 1
B20: Backend Unit Test | C20: =COUNTIF('Test Cases'!$B$2:$B$300,B20) -> 17 | D20: =COUNTIFS('Test Cases'!$B$2:$B$300,$B20,'Test Cases'!$I$2:$I$300,"ผ่าน") -> 16 | E20: =COUNTIFS('Test Cases'!$B$2:$B$300,$B20,'Test Cases'!$I$2:$I$300,"ไม่ผ่าน") -> 1 | F20: =COUNTIFS('Test Cases'!$B$2:$B$300,$B20,'Test Cases'!$I$2:$I$300,"ข้าม") -> 0 | G20: =COUNTIFS('Test Cases'!$B$2:$B$300,$B20,'Test Cases'!$I$2:$I$300,"บล็อก") -> 0 | H20: =COUNTIFS('Test Cases'!$B$2:$B$300,$B20,'Test Cases'!$I$2:$I$300,"ยังไม่ทดสอบ") -> 0 | I20: =IF(C20=0,0,D20/C20) -> 0.94117647
B21: ล็อกอิน Google (ทดสอบเอง) | C21: =COUNTIF('Test Cases'!$B$2:$B$300,B21) -> 7 | D21: =COUNTIFS('Test Cases'!$B$2:$B$300,$B21,'Test Cases'!$I$2:$I$300,"ผ่าน") -> 0 | E21: =COUNTIFS('Test Cases'!$B$2:$B$300,$B21,'Test Cases'!$I$2:$I$300,"ไม่ผ่าน") -> 0 | F21: =COUNTIFS('Test Cases'!$B$2:$B$300,$B21,'Test Cases'!$I$2:$I$300,"ข้าม") -> 0 | G21: =COUNTIFS('Test Cases'!$B$2:$B$300,$B21,'Test Cases'!$I$2:$I$300,"บล็อก") -> 0 | H21: =COUNTIFS('Test Cases'!$B$2:$B$300,$B21,'Test Cases'!$I$2:$I$300,"ยังไม่ทดสอบ") -> 7 | I21: =IF(C21=0,0,D21/C21) -> 0
B22: สมัคร/ล็อกอินอีเมล, LINE (ทดสอบเอง) | C22: =COUNTIF('Test Cases'!$B$2:$B$300,B22) -> 7 | D22: =COUNTIFS('Test Cases'!$B$2:$B$300,$B22,'Test Cases'!$I$2:$I$300,"ผ่าน") -> 0 | E22: =COUNTIFS('Test Cases'!$B$2:$B$300,$B22,'Test Cases'!$I$2:$I$300,"ไม่ผ่าน") -> 0 | F22: =COUNTIFS('Test Cases'!$B$2:$B$300,$B22,'Test Cases'!$I$2:$I$300,"ข้าม") -> 0 | G22: =COUNTIFS('Test Cases'!$B$2:$B$300,$B22,'Test Cases'!$I$2:$I$300,"บล็อก") -> 0 | H22: =COUNTIFS('Test Cases'!$B$2:$B$300,$B22,'Test Cases'!$I$2:$I$300,"ยังไม่ทดสอบ") -> 7 | I22: =IF(C22=0,0,D22/C22) -> 0
B23: ฟีเจอร์หลังล็อกอิน (อัตโนมัติ + ทดสอบเอง) | C23: =COUNTIF('Test Cases'!$B$2:$B$300,B23) -> 49 | D23: =COUNTIFS('Test Cases'!$B$2:$B$300,$B23,'Test Cases'!$I$2:$I$300,"ผ่าน") -> 47 | E23: =COUNTIFS('Test Cases'!$B$2:$B$300,$B23,'Test Cases'!$I$2:$I$300,"ไม่ผ่าน") -> 0 | F23: =COUNTIFS('Test Cases'!$B$2:$B$300,$B23,'Test Cases'!$I$2:$I$300,"ข้าม") -> 1 | G23: =COUNTIFS('Test Cases'!$B$2:$B$300,$B23,'Test Cases'!$I$2:$I$300,"บล็อก") -> 0 | H23: =COUNTIFS('Test Cases'!$B$2:$B$300,$B23,'Test Cases'!$I$2:$I$300,"ยังไม่ทดสอบ") -> 1 | I23: =IF(C23=0,0,D23/C23) -> 0.95918367
B24: ข้ามเบราว์เซอร์/อุปกรณ์ (ทดสอบเอง) | C24: =COUNTIF('Test Cases'!$B$2:$B$300,B24) -> 6 | D24: =COUNTIFS('Test Cases'!$B$2:$B$300,$B24,'Test Cases'!$I$2:$I$300,"ผ่าน") -> 0 | E24: =COUNTIFS('Test Cases'!$B$2:$B$300,$B24,'Test Cases'!$I$2:$I$300,"ไม่ผ่าน") -> 0 | F24: =COUNTIFS('Test Cases'!$B$2:$B$300,$B24,'Test Cases'!$I$2:$I$300,"ข้าม") -> 0 | G24: =COUNTIFS('Test Cases'!$B$2:$B$300,$B24,'Test Cases'!$I$2:$I$300,"บล็อก") -> 0 | H24: =COUNTIFS('Test Cases'!$B$2:$B$300,$B24,'Test Cases'!$I$2:$I$300,"ยังไม่ทดสอบ") -> 6 | I24: =IF(C24=0,0,D24/C24) -> 0
B25: รวม | C25: =SUM(C17:C24) -> 114 | D25: =SUM(D17:D24) -> 91 | E25: =SUM(E17:E24) -> 1 | F25: =SUM(F17:F24) -> 1 | G25: =SUM(G17:G24) -> 0 | H25: =SUM(H17:H24) -> 21 | I25: =IF(C25=0,0,D25/C25) -> 0.79824561
B27: แยกตามวิธีทดสอบ
B28: วิธี | C28: รวม | D28: ผ่าน | E28: ยังไม่ทดสอบ
B29: อัตโนมัติ | C29: =COUNTIF('Test Cases'!$G$2:$G$300,B29) -> 82 | D29: =COUNTIFS('Test Cases'!$G$2:$G$300,$B29,'Test Cases'!$I$2:$I$300,"ผ่าน") -> 80 | E29: =COUNTIFS('Test Cases'!$G$2:$G$300,$B29,'Test Cases'!$I$2:$I$300,"ยังไม่ทดสอบ") -> 0
B30: ทดสอบเอง | C30: =COUNTIF('Test Cases'!$G$2:$G$300,B30) -> 32 | D30: =COUNTIFS('Test Cases'!$G$2:$G$300,$B30,'Test Cases'!$I$2:$I$300,"ผ่าน") -> 11 | E30: =COUNTIFS('Test Cases'!$G$2:$G$300,$B30,'Test Cases'!$I$2:$I$300,"ยังไม่ทดสอบ") -> 21
B33: วิธีใช้
B34: 1) ไปที่ชีต Test Cases แถวที่วิธีทดสอบเป็น 'ทดสอบเอง' ทำตามขั้นตอนแล้วเทียบกับผลที่คาดหวัง
B35: 2) กรอกช่องสีเหลืองอ่อน 4 ช่อง: สถานะ (เลือกจากรายการ), วันที่ทดสอบ, ผู้ทดสอบ, หมายเหตุ / ผลที่เกิดขึ้นจริง
B36: 3) ถ้าไม่ผ่าน ให้เลือก 'ไม่ผ่าน' และจดสิ่งที่เห็นจริงในหมายเหตุ (แนบ error / ภาพหน้าจอ)
B37: 4) แถวอัตโนมัติ: รัน cd frontend/e2e && npm test แล้วอัปเดตสถานะจากผลที่ได้ (ชื่อเทสต์มีรหัส TC-… ตรงกับคอลัมน์ รหัส)
B38: 5) แถว BE-UT: รันใน repo backend ด้วย ./gradlew test --tests "*UserServiceTest"
B39: 6) ชีต Bug ที่พบ ใช้ดูว่าบั๊กแต่ละตัวมีเทสต์อะไรกันไม่ให้กลับมา
B41: ตัวอย่างการกรอก (แถวทดสอบเอง)
B42: รหัส | C42: สถานะ | D42: วันที่ทดสอบ | E42: ผู้ทดสอบ | F42: หมายเหตุ / ผลที่เกิดขึ้นจริง
B43: M-G01 (ตัวอย่าง) | C43: ผ่าน | D43: 46310 | E43: สรานุช | F43: เข้า Home ได้ มีหมวดหมู่ 10 หมวด ไม่มี 401
B45: หมายเหตุ (อัปเดต 2026-10-14): ชุด UI/API ทั่วไปรันบน production ส่วนเคสที่ต้องใช้รหัสผ่าน/JWT secret/แก้ข้อมูล (TC-EM, TC-AUTH, TC-FT, TC-UF) รันบน localhost เท่านั้น | e2e ทั้งชุดบน localhost รอบล่าสุด: ผ่าน 74 ข้าม 1 ตก 1 (ตก = TC-FT-21 ก่อนแก้ ปัจจุบันแก้แล้วและรันซ้ำผ่าน) | unit test ทั้งโปรเจกต์: 183 ข้อ ตก 21 ข้อที่ตกมาแต่เดิม
B46: บัญชีทดสอบอีเมลที่ยืนยันแล้ว: Soranut459@gmail.com (รหัสผ่านเก็บใน frontend/e2e/.env ที่ไม่ถูก commit ไม่เก็บในไฟล์นี้)

Sheet Test Cases
A1: รหัส | B1: กลุ่ม | C1: หัวข้อ | D1: ขั้นตอน | E1: ผลที่คาดหวัง | F1: ความสำคัญ | G1: วิธีทดสอบ | H1: ที่มาของเทสต์อัตโนมัติ | I1: สถานะ | J1: วันที่ทดสอบ | K1: ผู้ทดสอบ | L1: หมายเหตุ / ผลที่เกิดขึ้นจริง
A2: TC-UI-01 | B2: หน้า Login (UI อัตโนมัติ) | C2: โหลดหน้าเว็บไม่มี error | D2: 1. เปิดเว็บ 2. รอ Flutter โหลดเสร็จ 3. ดู console | E2: ไม่มี console.error / pageerror และไม่มีข้อความ Google origin ไม่ถูกต้อง | F2: สูง | G2: อัตโนมัติ | H2: frontend/e2e/tests/ui.spec.ts | I2: ผ่าน | J2: 46309 | K2: Playwright (auto)
A3: TC-UI-02 | B3: หน้า Login (UI อัตโนมัติ) | C3: หน้า Login แสดงส่วนประกอบครบ | D3: 1. เปิดเว็บ | E3: เห็น FINANCE CARE, แท็บเข้าสู่ระบบ/สมัครสมาชิก, ปุ่ม LINE, ปุ่ม Google, ช่องอีเมล, ช่องรหัสผ่าน | F3: สูง | G3: อัตโนมัติ | H3: frontend/e2e/tests/ui.spec.ts | I3: ผ่าน | J3: 46309 | K3: Playwright (auto)
A4: TC-UI-03 | B4: หน้า Login (UI อัตโนมัติ) | C4: สลับไปแท็บสมัครสมาชิก | D4: 1. เปิดเว็บ 2. กดแท็บ สมัครสมาชิก | E4: มีช่องยืนยันรหัสผ่านและปุ่มสร้างบัญชี | F4: กลาง | G4: อัตโนมัติ | H4: frontend/e2e/tests/ui.spec.ts | I4: ผ่าน | J4: 46309 | K4: Playwright (auto)
A5: TC-UI-04 | B5: หน้า Login (UI อัตโนมัติ) | C5: กดเข้าสู่ระบบโดยไม่กรอกข้อมูล | D5: 1. เปิดเว็บ 2. กดปุ่ม เข้าสู่ระบบ โดยไม่กรอกอะไร | E5: แสดงข้อความ กรุณากรอกข้อมูล | F5: กลาง | G5: อัตโนมัติ | H5: frontend/e2e/tests/ui.spec.ts | I5: ผ่าน | J5: 46309 | K5: Playwright (auto)
A6: TC-UI-05 | B6: หน้า Login (UI อัตโนมัติ) | C6: อีเมล/รหัสผ่านผิด | D6: 1. กรอกอีเมลที่ไม่มีในระบบ + รหัสผ่านมั่ว 2. กดเข้าสู่ระบบ | E6: แสดง dialog อีเมลหรือรหัสผ่านไม่ถูกต้อง และไม่เข้าหน้า home | F6: สูง | G6: อัตโนมัติ | H6: frontend/e2e/tests/ui.spec.ts | I6: ผ่าน | J6: 46309 | K6: Playwright (auto)
A7: TC-UI-06 | B7: หน้า Login (UI อัตโนมัติ) | C7: ไม่มี token แล้วเข้า home (Demo Bypass) | D7: 1. เปิดเว็บ (ยังไม่ล็อกอิน) 2. กด Demo Bypass | E7: ถูกเด้งกลับหน้า login และไม่มี error ที่ไม่ได้จัดการ | F7: กลาง | G7: อัตโนมัติ | H7: frontend/e2e/tests/ui.spec.ts | I7: ผ่าน | J7: 46309 | K7: Playwright (auto)
A8: TC-UI-07 | B8: หน้า Login (UI อัตโนมัติ) | C8: หน้าจอมือถือ 390x844 | D8: 1. เปิดเว็บด้วยขนาดจอมือถือ | E8: ปุ่มใช้งานได้ และไม่มี scroll แนวนอน | F8: กลาง | G8: อัตโนมัติ | H8: frontend/e2e/tests/ui.spec.ts | I8: ผ่าน | J8: 46309 | K8: Playwright (auto)
A9: TC-GG-01 | B9: ปุ่ม Google (อัตโนมัติ) | C9: ปุ่ม Google วางทับปุ่มที่เห็นและสูงเท่าปุ่ม LINE | D9: 1. เปิดเว็บ 2. วัดขนาดปุ่มของ Google เทียบปุ่ม LINE | E9: iframe ของ Google กว้างกว่า 200px และความสูงต่างจากปุ่ม LINE ไม่เกิน 4px | F9: กลาง | G9: อัตโนมัติ | H9: frontend/e2e/tests/ui.spec.ts | I9: ผ่าน | J9: 46309 | K9: Playwright (auto)
A10: TC-GG-02 | B10: ปุ่ม Google (อัตโนมัติ) | C10: กดปุ่ม Google แล้วไม่ขึ้น origin_mismatch | D10: 1. เปิดเว็บ 2. คลิกปุ่ม Google | E10: เปิด popup accounts.google.com โดยไม่ไปหน้า oauth/error / origin_mismatch | F10: สูง | G10: อัตโนมัติ | H10: frontend/e2e/tests/ui.spec.ts | I10: ผ่าน | J10: 46309 | K10: Playwright (auto) | L10: ถ้ารันกับ localhost ต้องเพิ่ม origin ใน Google Cloud ก่อน ไม่งั้นข้อนี้จะตก (ถูกต้อง)
A11: TC-API-01 | B11: Backend API (อัตโนมัติ) | C11: Backend ตอบ (swagger) | D11: GET /api/swagger-ui/index.html | E11: HTTP 200 | F11: สูง | G11: อัตโนมัติ | H11: frontend/e2e/tests/api.spec.ts | I11: ผ่าน | J11: 46309 | K11: Playwright (auto)
A12: TC-API-02 | B12: Backend API (อัตโนมัติ) | C12: CORS preflight จากเว็บ | D12: OPTIONS /api/auth/login/google พร้อม Origin ของเว็บ | E12: 200 และ allow-origin ตรงกับเว็บ, allow-headers มี authorization | F12: สูง | G12: อัตโนมัติ | H12: frontend/e2e/tests/api.spec.ts | I12: ผ่าน | J12: 46309 | K12: Playwright (auto)
A13: TC-API-03 | B13: Backend API (อัตโนมัติ) | C13: ไม่มี token เรียก API ที่ต้องล็อกอิน (4 endpoint) | D13: GET /api/debts, /categories, /debt-types, /repayment-types โดยไม่ส่ง token | E13: HTTP 401 ทุกอัน | F13: สูง | G13: อัตโนมัติ | H13: frontend/e2e/tests/api.spec.ts | I13: ผ่าน | J13: 46309 | K13: Playwright (auto)
A14: TC-API-04 | B14: Backend API (อัตโนมัติ) | C14: token มั่ว ๆ | D14: GET /api/debts ด้วย Bearer not-a-real-token | E14: HTTP 401 (ไม่ใช่ 500) | F14: สูง | G14: อัตโนมัติ | H14: frontend/e2e/tests/api.spec.ts | I14: ผ่าน | J14: 46309 | K14: Playwright (auto)
A15: TC-API-05 | B15: Backend API (อัตโนมัติ) | C15: login/google ด้วย JWT ที่ไม่ถูกต้อง | D15: POST /api/auth/login/google ด้วย JWT ปลอม | E15: HTTP 401 | F15: สูง | G15: อัตโนมัติ | H15: frontend/e2e/tests/api.spec.ts | I15: ผ่าน | J15: 46309 | K15: Playwright (auto)
A16: TC-API-06 | B16: Backend API (อัตโนมัติ) | C16: login/google ด้วย idToken ที่ไม่ใช่ JWT | D16: POST ด้วย idToken = x | E16: HTTP 401 | F16: สูง | G16: อัตโนมัติ | H16: frontend/e2e/tests/api.spec.ts | I16: ผ่าน | J16: 46309 | K16: Playwright (auto) | L16: เคยเป็น 500 แก้แล้ว (commit 2959510)
A17: TC-API-07 | B17: Backend API (อัตโนมัติ) | C17: login/google ไม่มี idToken | D17: POST ด้วย body {} | E17: HTTP 401 | F17: สูง | G17: อัตโนมัติ | H17: frontend/e2e/tests/api.spec.ts | I17: ผ่าน | J17: 46309 | K17: Playwright (auto) | L17: เคยเป็น 500 แก้แล้ว (commit 2959510)
A18: TC-API-08 | B18: Backend API (อัตโนมัติ) | C18: login อีเมลที่ไม่มีอยู่ | D18: POST /api/auth/login ด้วยอีเมลที่ไม่มี | E18: HTTP 401 | F18: กลาง | G18: อัตโนมัติ | H18: frontend/e2e/tests/api.spec.ts | I18: ผ่าน | J18: 46309 | K18: Playwright (auto)
A19: TC-API-09 | B19: Backend API (อัตโนมัติ) | C19: login/google idToken เป็นสตริงว่าง | D19: POST ด้วย idToken = ว่าง | E19: HTTP 401 | F19: กลาง | G19: อัตโนมัติ | H19: frontend/e2e/tests/api.spec.ts | I19: ผ่าน | J19: 46309 | K19: Playwright (auto)
A20: TC-AUTH-01 | B20: Backend API (อัตโนมัติ) | C20: ผู้ใช้ Google (ไม่มีรหัสผ่าน) เรียก API ที่ต้องมี token (5 endpoint) | D20: ตั้ง E2E_JWT_SECRET และ E2E_USER_EMAIL แล้วรัน npm test | E20: GET /debts, /debt-types, /repayment-types, /categories, /receiver-mappings ได้ 200 | F20: สูง | G20: อัตโนมัติ | H20: frontend/e2e/tests/auth-api.spec.ts | I20: ผ่าน | J20: 46309 | K20: Playwright (auto, localhost) | L20: ผ่านบน stack ในเครื่อง กับผู้ใช้ที่ password_hash เป็น NULL และ JWT ที่ลงนามด้วย secret ของ backend ในเครื่อง ยังไม่ได้รันบน production
A21: TC-AUTH-02 | B21: Backend API (อัตโนมัติ) | C21: token ที่ลงนามด้วย secret ผิด | D21: ตั้ง env แบบเดียวกับ TC-AUTH-01 | E21: HTTP 401 | F21: กลาง | G21: อัตโนมัติ | H21: frontend/e2e/tests/auth-api.spec.ts | I21: ผ่าน | J21: 46309 | K21: Playwright (auto, localhost) | L21: ผ่านบน stack ในเครื่อง ยังไม่ได้รันบน production
A22: BE-UT-01 | B22: Backend Unit Test | C22: loginWithGoogle: idToken เป็น null | D22: JUnit | E22: BusinessException 401 | F22: สูง | G22: อัตโนมัติ | H22: backend: UserServiceTest.testLoginWithGoogle_NullToken_Returns401 | I22: ผ่าน | J22: 46309 | K22: JUnit (auto)
A23: BE-UT-02 | B23: Backend Unit Test | C23: loginWithGoogle: idToken ว่าง | D23: JUnit | E23: BusinessException 401 | F23: สูง | G23: อัตโนมัติ | H23: backend: UserServiceTest.testLoginWithGoogle_BlankToken_Returns401 | I23: ผ่าน | J23: 46309 | K23: JUnit (auto)
A24: BE-UT-03 | B24: Backend Unit Test | C24: loginWithGoogle: idToken ไม่ใช่ JWT | D24: JUnit | E24: BusinessException 401 | F24: สูง | G24: อัตโนมัติ | H24: backend: UserServiceTest.testLoginWithGoogle_MalformedToken_Returns401 | I24: ผ่าน | J24: 46309 | K24: JUnit (auto)
A25: BE-UT-04 | B25: Backend Unit Test | C25: ผู้ใช้ไม่มีรหัสผ่านโหลดเป็น UserDetails ได้ | D25: JUnit | E25: ไม่ throw และ password เป็นสตริงว่าง | F25: สูง | G25: อัตโนมัติ | H25: backend: UserServiceTest.testLoadUserByUsername_UserWithoutPassword_DoesNotThrow | I25: ผ่าน | J25: 46309 | K25: JUnit (auto) | L25: กันบั๊ก 401 ทุก request หลังล็อกอินด้วย Google
A26: BE-UT-05 | B26: Backend Unit Test | C26: งบเริ่มต้นของผู้ใช้ใหม่มี month/year | D26: JUnit | E26: ทุก Budget ที่สร้างมี month 1-12 และ year | F26: สูง | G26: อัตโนมัติ | H26: backend: UserServiceTest.testCreateDefaultCategories_BudgetsHaveMonthAndYear | I26: ผ่าน | J26: 46309 | K26: JUnit (auto) | L26: กันบั๊ก null value in column month
A27: BE-UT-06 | B27: Backend Unit Test | C27: UserServiceTest เดิม 4 ข้อ (สมัคร / OTP) | D27: JUnit | E27: ผ่านทั้งหมด | F27: กลาง | G27: อัตโนมัติ | H27: backend: UserServiceTest.testRegisterUser_*, testVerifyOtp_* | I27: ผ่าน | J27: 46309 | K27: JUnit (auto)
A28: BE-UT-07 | B28: Backend Unit Test | C28: Unit test ทั้งโปรเจกต์ backend | D28: รันใน repo financecare-backend-deploy: ./gradlew test | E28: ผ่านทั้งหมด | F28: กลาง | G28: อัตโนมัติ | H28: backend: ./gradlew test (43 คลาส) | I28: ไม่ผ่าน | J28: 46309 | K28: JUnit (auto) | L28: รันแล้ว 183 ข้อ: ผ่าน 162 ตก 21 | ทั้ง 21 ข้อตกมาก่อนที่ผมจะแก้อะไร (รันบน commit 993a11b ได้ตก 23 ข้อชุดเดียวกัน ผมแก้ DebtServiceTest ได้ 2 ข้อ) ไม่ได้เกิดจากการแก้ของผม | ตก: CapstoneApplicationTests 1, DebtControllerTest 5, DebtTypeControllerTest 1, JobControllerTest 4, RepaymentTypeControllerTest 1, NotificationServiceTest 2, OcrServiceTest 1, ReceiverMappingServiceTest 1, RepaymentBugReproductionTest 1, RepaymentPlanServiceTest 1, RepaymentServiceTest 1, SlipServiceTest 2
A29: M-G01 | B29: ล็อกอิน Google (ทดสอบเอง) | C29: ล็อกอิน Google ครั้งแรก (บัญชีที่ไม่เคยมีในระบบ) | D29: 1. เปิดเว็บใน Incognito 2. กดปุ่ม ดำเนินการต่อด้วย Google 3. เลือกบัญชีที่ยังไม่เคยใช้กับแอป | E29: เข้าหน้า Home ได้ ไม่มี dialog error และไม่ถูกเด้งกลับ login มีหมวดหมู่เริ่มต้นรายรับ 2 และรายจ่าย 8 หมวด | F29: สูง | G29: ทดสอบเอง | H29: - | I29: ยังไม่ทดสอบ | L29: ข้อนี้คือ flow ที่เคยพังหลายรอบ ต้องทดสอบด้วยตัวเองเพราะ Google บล็อกบอต
A30: M-G02 | B30: ล็อกอิน Google (ทดสอบเอง) | C30: ล็อกอิน Google ซ้ำด้วยบัญชีเดิม | D30: 1. ล็อกอิน Google ด้วยบัญชีที่เคยล็อกอินแล้ว | E30: เข้า Home ได้ ข้อมูลเดิมยังอยู่ และหมวดหมู่ไม่ซ้ำ | F30: สูง | G30: ทดสอบเอง | H30: - | I30: ยังไม่ทดสอบ
A31: M-G03 | B31: ล็อกอิน Google (ทดสอบเอง) | C31: รีเฟรชหน้า (F5) หลังล็อกอิน | D31: 1. ล็อกอิน Google 2. กด F5 | E31: ยังอยู่ในระบบ ไม่ถูกเด้งกลับ login (ถ้าแอปไม่ได้ออกแบบแบบนี้ ให้จดเป็นข้อสังเกต) | F31: กลาง | G31: ทดสอบเอง | H31: - | I31: ยังไม่ทดสอบ
A32: M-G04 | B32: ล็อกอิน Google (ทดสอบเอง) | C32: ไม่เจอ 401 หลังล็อกอิน | D32: 1. เปิด DevTools > Network 2. ล็อกอิน Google 3. เปิดแต่ละหน้าหลัก | E32: ไม่มี request ที่ตอบ 401/500 และไม่มี error ใน Console | F32: สูง | G32: ทดสอบเอง | H32: - | I32: ยังไม่ทดสอบ | L32: เคยเจอ 401 ทุก request เพราะผู้ใช้ไม่มีรหัสผ่าน (แก้แล้ว)
A33: M-G05 | B33: ล็อกอิน Google (ทดสอบเอง) | C33: ปิด popup ของ Google กลางทาง | D33: 1. กดปุ่ม Google 2. ปิด popup โดยไม่เลือกบัญชี | E33: แอปไม่ค้าง ไม่เข้าหน้า home และกดลองใหม่ได้ | F33: ต่ำ | G33: ทดสอบเอง | H33: - | I33: ยังไม่ทดสอบ
A34: M-G06 | B34: ล็อกอิน Google (ทดสอบเอง) | C34: ออกจากระบบแล้วล็อกอิน Google อีกครั้ง | D34: 1. ออกจากระบบ 2. ล็อกอิน Google อีกครั้ง | E34: เข้า Home ได้ตามปกติ | F34: กลาง | G34: ทดสอบเอง | H34: - | I34: ยังไม่ทดสอบ
A35: M-G07 | B35: ล็อกอิน Google (ทดสอบเอง) | C35: ล็อกอิน Google ตอน Render เพิ่งตื่น (cold start) | D35: 1. ปล่อยไว้ 15+ นาทีให้ service sleep 2. ล็อกอิน Google | E35: request แรกช้า (ประมาณ 50 วินาที) แต่สำเร็จ ไม่ขึ้น error | F35: กลาง | G35: ทดสอบเอง | H35: - | I35: ยังไม่ทดสอบ
A36: M-E01 | B36: สมัคร/ล็อกอินอีเมล, LINE (ทดสอบเอง) | C36: สมัครสมาชิกด้วยอีเมล + OTP | D36: 1. แท็บ สมัครสมาชิก 2. กรอกอีเมลจริง รหัสผ่าน ยืนยันรหัสผ่าน 3. กดสร้างบัญชี 4. กรอก OTP จากอีเมล | E36: สมัครสำเร็จและเข้าใช้งานได้ ได้รับอีเมล OTP | F36: สูง | G36: ทดสอบเอง | H36: - | I36: ยังไม่ทดสอบ | L36: บนเว็บ deploy ตอนนี้ยังไม่ได้รับ OTP จนกว่าจะตั้ง Brevo (ดู M-E07)
A37: M-E02 | B37: สมัคร/ล็อกอินอีเมล, LINE (ทดสอบเอง) | C37: สมัครด้วยอีเมลที่มีอยู่แล้ว | D37: 1. สมัครด้วยอีเมลที่เคยสมัคร | E37: แสดงข้อความว่าอีเมลซ้ำ ไม่สร้างบัญชีใหม่ | F37: กลาง | G37: ทดสอบเอง | H37: - | I37: ยังไม่ทดสอบ
A38: M-E03 | B38: สมัคร/ล็อกอินอีเมล, LINE (ทดสอบเอง) | C38: รหัสผ่านไม่ตรงกับช่องยืนยัน | D38: 1. กรอกรหัสผ่านและยืนยันรหัสผ่านไม่เหมือนกัน 2. กดสร้างบัญชี | E38: ไม่ให้สมัคร และแจ้งให้แก้ | F38: กลาง | G38: ทดสอบเอง | H38: - | I38: ยังไม่ทดสอบ
A39: M-E04 | B39: สมัคร/ล็อกอินอีเมล, LINE (ทดสอบเอง) | C39: OTP ผิดหรือหมดอายุ | D39: 1. กรอก OTP ผิด 2. ลองอีกครั้งหลัง OTP หมดอายุ | E39: แจ้ง error ชัดเจน ไม่เข้าใช้งาน | F39: กลาง | G39: ทดสอบเอง | H39: - | I39: ยังไม่ทดสอบ
A40: M-E05 | B40: สมัคร/ล็อกอินอีเมล, LINE (ทดสอบเอง) | C40: ล็อกอินด้วยอีเมล/รหัสผ่านที่ถูกต้อง | D40: 1. กรอกบัญชีที่สมัครไว้ 2. กดเข้าสู่ระบบ | E40: เข้า Home ได้ ไม่มี 401 | F40: สูง | G40: ทดสอบเอง | H40: - | I40: ยังไม่ทดสอบ | L40: บัญชีทดสอบ: Soranut459@gmail.com (รหัสผ่านไม่เก็บในไฟล์นี้)
A41: M-E06 | B41: สมัคร/ล็อกอินอีเมล, LINE (ทดสอบเอง) | C41: ล็อกอิน LINE บน web | D41: 1. กดปุ่ม ดำเนินการต่อด้วย LINE | E41: จดผลที่เกิดขึ้นจริง (ยังไม่ทราบว่า LINE SDK รองรับบน web) | F41: ต่ำ | G41: ทดสอบเอง | H41: - | I41: ยังไม่ทดสอบ | L41: โค้ดฝั่ง backend ใช้ผู้ใช้ไม่มีรหัสผ่านเหมือน Google จึงควรได้ผลจากบั๊กที่แก้ไปแล้วด้วย
A42: M-F01 | B42: ฟีเจอร์หลังล็อกอิน (อัตโนมัติ + ทดสอบเอง) | C42: หน้า Home โหลดข้อมูลสรุป | D42: 1. ล็อกอิน 2. ดูหน้า Home | E42: แสดงข้อมูลสรุป ไม่มี error และ spinner ไม่ค้าง | F42: สูง | G42: ทดสอบเอง | H42: frontend/e2e/tests/ui-flows.spec.ts (TC-UF-01) | I42: ผ่าน | J42: 46309 | K42: Playwright (auto, localhost) | L42: ทดสอบอัตโนมัติผ่านหน้าจอจริงบน localhost | ยอดรวม จำนวนหนี้ และยอดขั้นต่ำบน Home ตรงกับข้อมูลจริงใน API ไม่มี 4xx/5xx
A43: M-F02 | B43: ฟีเจอร์หลังล็อกอิน (อัตโนมัติ + ทดสอบเอง) | C43: เพิ่มรายการรายรับ/รายจ่าย | D43: 1. เปิดหน้าเพิ่มรายการ 2. เลือกหมวดหมู่ กรอกจำนวนเงิน 3. บันทึก | E43: บันทึกสำเร็จ รายการขึ้นในรายการธุรกรรม ยอดงบเปลี่ยนถูกต้อง | F43: สูง | G43: ทดสอบเอง | H43: frontend/e2e/tests/ui-flows.spec.ts (TC-UF-02) | I43: ผ่าน | J43: 46309 | K43: Playwright (auto, localhost) | L43: ทดสอบอัตโนมัติผ่านหน้าจอจริงบน localhost | เพิ่มรายจ่ายผ่าน dialog ได้ รายการและยอดงบอัปเดตถูกต้อง
A44: M-F03 | B44: ฟีเจอร์หลังล็อกอิน (อัตโนมัติ + ทดสอบเอง) | C44: ดู/แก้ไขรายการธุรกรรม | D44: 1. เปิดรายการธุรกรรม 2. เปิดรายละเอียด 3. แก้ไขหรือลบ | E44: ข้อมูลอัปเดตถูกต้อง ยอดรวมคำนวณใหม่ | F44: กลาง | G44: ทดสอบเอง | H44: frontend/e2e/tests/ui-flows.spec.ts (TC-UF-03) | I44: ผ่าน | J44: 46309 | K44: Playwright (auto, localhost) | L44: ทดสอบอัตโนมัติผ่านหน้าจอจริงบน localhost | เปิดรายการ ดูรายละเอียด แก้จำนวนเงินได้ งบปรับตามส่วนต่าง | พบและแก้บั๊ก 2 ข้อระหว่างทดสอบ (ดูชีต Bug ที่พบ ข้อ 15-16)
A45: M-F04 | B45: ฟีเจอร์หลังล็อกอิน (อัตโนมัติ + ทดสอบเอง) | C45: ตั้งงบรายหมวดหมู่ | D45: 1. เปิดหน้างบประมาณ 2. แก้วงเงินของหมวด 3. บันทึก | E45: บันทึกได้ และแสดงในเดือนปัจจุบัน | F45: กลาง | G45: ทดสอบเอง | H45: frontend/e2e/tests/ui-flows.spec.ts (TC-UF-04) | I45: ผ่าน | J45: 46309 | K45: Playwright (auto, localhost) | L45: ทดสอบอัตโนมัติผ่านหน้าจอจริงบน localhost | ตั้งวงเงินงบรายหมวดผ่านหน้าจอได้
A46: M-F05 | B46: ฟีเจอร์หลังล็อกอิน (อัตโนมัติ + ทดสอบเอง) | C46: เพิ่มหนี้ | D46: 1. เปิดหน้าเพิ่มหนี้ 2. กรอกข้อมูลหนี้ให้ครบ 3. บันทึก | E46: หนี้ขึ้นในรายการหนี้ ข้อมูลตรงกับที่กรอก | F46: สูง | G46: ทดสอบเอง | H46: frontend/e2e/tests/ui-flows.spec.ts (TC-UF-05) | I46: ผ่าน | J46: 46309 | K46: Playwright (auto, localhost) | L46: ทดสอบอัตโนมัติผ่านหน้าจอจริงบน localhost | ฟอร์ม 3 ขั้นสร้างหนี้ได้ ข้อมูลใน API ตรงกับที่กรอก
A47: M-F06 | B47: ฟีเจอร์หลังล็อกอิน (อัตโนมัติ + ทดสอบเอง) | C47: แก้ไข/ดูรายละเอียดหนี้ | D47: 1. เปิดหนี้ที่มีอยู่ 2. ดูรายละเอียดและแก้ไข | E47: ข้อมูลอัปเดตถูกต้อง | F47: กลาง | G47: ทดสอบเอง | H47: frontend/e2e/tests/ui-flows.spec.ts (TC-UF-06) | I47: ผ่าน | J47: 46309 | K47: Playwright (auto, localhost) | L47: ทดสอบอัตโนมัติผ่านหน้าจอจริงบน localhost | แก้ชื่อหนี้และลบหนี้ที่ยังไม่เคยจ่ายผ่านเมนูการ์ดได้ | ลบหนี้ที่เคยจ่ายแล้วทำได้แล้วหลังแก้บั๊กข้อ 11 แต่แก้ไขเพื่อปิดการใช้งานหนี้ยังไม่ได้ (บั๊กข้อ 17)
A48: M-F07 | B48: ฟีเจอร์หลังล็อกอิน (อัตโนมัติ + ทดสอบเอง) | C48: จ่ายหนี้ | D48: 1. เปิดหน้าจ่ายหนี้ 2. กรอกจำนวนเงินและบันทึก | E48: ยอดหนี้คงเหลือลดลงถูกต้อง และมีประวัติการจ่าย | F48: สูง | G48: ทดสอบเอง | H48: frontend/e2e/tests/ui-flows.spec.ts (TC-UF-07) | I48: ผ่าน | J48: 46309 | K48: Playwright (auto, localhost) | L48: ทดสอบอัตโนมัติผ่านหน้าจอจริงบน localhost | จ่ายหนี้ผ่านหน้าจอได้ ยอดคงเหลือลดลง และมีประวัติการจ่าย
A49: M-F08 | B49: ฟีเจอร์หลังล็อกอิน (อัตโนมัติ + ทดสอบเอง) | C49: Simulator กลยุทธ์การชำระหนี้ | D49: 1. เปิดหน้า Simulator 2. เลือกกลยุทธ์และกรอกงบต่อเดือน | E49: แสดงแผนและผลการคำนวณได้ ไม่ error | F49: กลาง | G49: ทดสอบเอง | H49: frontend/e2e/tests/ui-flows.spec.ts (TC-UF-08) | I49: ผ่าน | J49: 46309 | K49: Playwright (auto, localhost) | L49: ทดสอบอัตโนมัติผ่านหน้าจอจริงบน localhost | ตั้งงบรายเดือน เลือกกลยุทธ์ จัดลำดับ แล้วไปถึงขั้นแสดงแผนได้
A50: M-F09 | B50: ฟีเจอร์หลังล็อกอิน (อัตโนมัติ + ทดสอบเอง) | C50: หน้าแจ้งเตือน | D50: 1. เปิดหน้าแจ้งเตือน | E50: แสดงรายการ/ว่างโดยไม่ error จำนวนที่ยังไม่อ่านถูกต้อง | F50: ต่ำ | G50: ทดสอบเอง | H50: frontend/e2e/tests/ui-flows.spec.ts (TC-UF-09) | I50: ผ่าน | J50: 46309 | K50: Playwright (auto, localhost) | L50: ทดสอบอัตโนมัติผ่านหน้าจอจริงบน localhost | ผ่านเฉพาะการเปิดหน้าและสลับแท็บ ยังไม่ได้ทดสอบเนื้อหาการแจ้งเตือนจริง (ไม่มีข้อมูลให้ทดสอบ)
A51: M-F10 | B51: ฟีเจอร์หลังล็อกอิน (อัตโนมัติ + ทดสอบเอง) | C51: อัปโหลดสลิป (OCR) | D51: 1. เปิดหน้าอัปโหลดสลิป 2. เลือกรูปสลิปจริง | E51: อ่านจำนวนเงิน/ผู้รับได้ถูกต้องและบันทึกเป็นรายการ | F51: กลาง | G51: ทดสอบเอง | H51: frontend/e2e/tests/ui-flows.spec.ts (TC-UF-10, TC-UF-10b) | I51: ยังไม่ทดสอบ | L51: ส่วน API ผ่านแล้ว (อัปโหลดรูปที่ไม่ใช่สลิปได้ผลที่ไม่ใช่ 500) แต่ทางหน้าจอยังไม่ได้ทดสอบ: เลือกไฟล์ผ่านเมนู 'เลือกจากแกลเลอรี่' แล้วแอปไม่ส่งรูปไป backend และมี pageerror ทั่วไป 1 รายการ ยังไม่ทราบว่าเป็นบั๊กของแอปหรือข้อจำกัดของการทดสอบอัตโนมัติ ต้องทดสอบด้วยมือ (ใช้รูปสลิปจริงด้วย) | ยังไม่ได้ทดสอบการอ่านสลิปจริง
A52: M-F11 | B52: ฟีเจอร์หลังล็อกอิน (อัตโนมัติ + ทดสอบเอง) | C52: ตั้งค่าผู้ใช้ | D52: 1. เปิดหน้าตั้งค่า 2. แก้ค่าและบันทึก 3. รีเฟรช | E52: ค่าที่บันทึกยังอยู่ | F52: ต่ำ | G52: ทดสอบเอง | H52: frontend/e2e/tests/ui-flows.spec.ts (TC-UF-11) | I52: ผ่าน | J52: 46309 | K52: Playwright (auto, localhost) | L52: ทดสอบอัตโนมัติผ่านหน้าจอจริงบน localhost | ผ่านเฉพาะการบันทึกเงินเดือน (ต้องยืนยันใน dialog) ยังไม่ได้ทดสอบเปิด/ปิดการแจ้งเตือนและเวลา
A53: M-F12 | B53: ฟีเจอร์หลังล็อกอิน (อัตโนมัติ + ทดสอบเอง) | C53: ออกจากระบบ | D53: 1. กดออกจากระบบ 2. กด Back ของเบราว์เซอร์ | E53: กลับหน้า login และเข้าหน้าที่ต้องล็อกอินไม่ได้ | F53: กลาง | G53: ทดสอบเอง | H53: frontend/e2e/tests/ui-flows.spec.ts (TC-UF-12) | I53: ผ่าน | J53: 46309 | K53: Playwright (auto, localhost) | L53: ทดสอบอัตโนมัติผ่านหน้าจอจริงบน localhost | ออกจากระบบแล้วกลับหน้า login และรีเฟรชแล้วยังไม่เข้าระบบ
A54: M-X01 | B54: ข้ามเบราว์เซอร์/อุปกรณ์ (ทดสอบเอง) | C54: Chrome (เวอร์ชันล่าสุด) | D54: 1. ล็อกอิน Google 2. ไล่ใช้งานหลัก | E54: ใช้งานได้ปกติ | F54: สูง | G54: ทดสอบเอง | H54: - | I54: ยังไม่ทดสอบ
A55: M-X02 | B55: ข้ามเบราว์เซอร์/อุปกรณ์ (ทดสอบเอง) | C55: Edge | D55: 1. ล็อกอิน Google 2. ไล่ใช้งานหลัก | E55: ใช้งานได้ปกติ | F55: กลาง | G55: ทดสอบเอง | H55: - | I55: ยังไม่ทดสอบ
A56: M-X03 | B56: ข้ามเบราว์เซอร์/อุปกรณ์ (ทดสอบเอง) | C56: Firefox | D56: 1. ล็อกอิน Google 2. ไล่ใช้งานหลัก | E56: ใช้งานได้ปกติ (ปุ่ม Google และ popup ไม่ถูกบล็อก) | F56: กลาง | G56: ทดสอบเอง | H56: - | I56: ยังไม่ทดสอบ
A57: M-X04 | B57: ข้ามเบราว์เซอร์/อุปกรณ์ (ทดสอบเอง) | C57: มือถือจริง (Android/iOS) | D57: 1. เปิดเว็บบนมือถือ 2. ล็อกอิน Google | E57: หน้าจอพอดี ปุ่มกดได้ ล็อกอินได้ | F57: กลาง | G57: ทดสอบเอง | H57: - | I57: ยังไม่ทดสอบ | L57: popup ของ Google อาจถูกบล็อกบนบางเบราว์เซอร์มือถือ
A58: M-X05 | B58: ข้ามเบราว์เซอร์/อุปกรณ์ (ทดสอบเอง) | C58: ปุ่ม Google บนจอกว้าง (> 400px) | D58: 1. เปิดเว็บบน desktop 2. ลองกดตรงขอบซ้าย/ขวาของปุ่ม | E58: ปุ่มที่เห็นกดได้ทั้งแถบ (ปุ่ม Google จำกัด 400px) | F58: ต่ำ | G58: ทดสอบเอง | H58: - | I58: ยังไม่ทดสอบ
A59: M-X06 | B59: ข้ามเบราว์เซอร์/อุปกรณ์ (ทดสอบเอง) | C59: ภาษาไทยแสดงถูกต้อง | D59: 1. ดูทุกหน้าหลัก | E59: ไม่มีตัวอักษรเป็นกล่อง ฟอนต์โหลดครบ | F59: ต่ำ | G59: ทดสอบเอง | H59: - | I59: ยังไม่ทดสอบ | L59: ในเบราว์เซอร์ทดสอบของผมฟอนต์ไทยเคยแสดงเป็นกล่อง เพราะโหลดฟอนต์จากเน็ตไม่ได้ ควรเช็คบนเครื่องจริง
A60: BE-UT-08 | B60: Backend Unit Test | C60: BrevoMailClient: ไม่เปิดใช้เมื่อไม่มี API key | D60: JUnit | E60: isEnabled() = false | F60: กลาง | G60: อัตโนมัติ | H60: backend: BrevoMailClientTest.notEnabledWithoutApiKey | I60: ผ่าน | J60: 46309 | K60: JUnit (auto) | L60: ถ้าไม่ตั้ง BREVO_API_KEY ระบบกลับไปใช้ SMTP เดิม
A61: BE-UT-09 | B61: Backend Unit Test | C61: BrevoMailClient: เปิดใช้เมื่อมี API key | D61: JUnit | E61: isEnabled() = true | F61: กลาง | G61: อัตโนมัติ | H61: backend: BrevoMailClientTest.enabledWhenApiKeySet | I61: ผ่าน | J61: 46309 | K61: JUnit (auto)
A62: BE-UT-10 | B62: Backend Unit Test | C62: BrevoMailClient: แจ้งชัดเจนเมื่อไม่ได้ตั้ง MAIL_FROM | D62: JUnit | E62: throw IllegalStateException ที่มีคำว่า MAIL_FROM | F62: กลาง | G62: อัตโนมัติ | H62: backend: BrevoMailClientTest.sendFailsClearlyWhenSenderMissing | I62: ผ่าน | J62: 46309 | K62: JUnit (auto)
A63: M-E07 | B63: สมัคร/ล็อกอินอีเมล, LINE (ทดสอบเอง) | C63: ได้รับอีเมล OTP จริงหลังตั้ง Brevo | D63: 1. ตั้ง BREVO_API_KEY และ MAIL_FROM บน Render แล้ว deploy 2. สมัครสมาชิกด้วยอีเมลจริงของคุณ 3. ดูกล่องจดหมาย (รวมถึง Spam) | E63: ได้รับอีเมลรหัส 6 หลักภายใน 1 นาที และกรอกแล้วผ่านการยืนยัน | F63: สูง | G63: ทดสอบเอง | H63: - | I63: ยังไม่ทดสอบ | L63: ก่อนหน้านี้ไม่ได้รับ OTP เพราะ Redis ต่อไม่ได้ และ Render ฟรีบล็อก SMTP (ดูชีต Bug ที่พบ ข้อ 8-9)
A64: TC-EM-01 | B64: Backend API (อัตโนมัติ) | C64: ล็อกอินด้วยอีเมล/รหัสผ่านที่ถูกต้อง (บัญชีที่ยืนยันแล้ว) | D64: POST /api/auth/login ด้วยบัญชีทดสอบ | E64: HTTP 200 ได้ accessToken และ refreshToken เป็น JWT ที่ไม่เหมือนกัน | F64: สูง | G64: อัตโนมัติ | H64: frontend/e2e/tests/account.spec.ts | I64: ผ่าน | J64: 46309 | K64: Playwright (auto, localhost) | L64: ผ่านบน stack ในเครื่อง (localhost: backend + Postgres + Redis + หน้าเว็บ) ด้วยบัญชีทดสอบที่สร้างขึ้นเอง ไม่ได้รันบน production
A65: TC-EM-02 | B65: Backend API (อัตโนมัติ) | C65: ล็อกอินแล้วเรียก API ที่ต้องมี token (4 endpoint) | D65: ล็อกอิน แล้ว GET /api/debts, /categories, /debt-types, /repayment-types ด้วย access token | E65: HTTP 200 ทุกอัน (ไม่ใช่ 401 หรือ 403 Email not verified) | F65: สูง | G65: อัตโนมัติ | H65: frontend/e2e/tests/account.spec.ts | I65: ผ่าน | J65: 46309 | K65: Playwright (auto, localhost) | L65: ผ่านบน stack ในเครื่อง (localhost: backend + Postgres + Redis + หน้าเว็บ) ด้วยบัญชีทดสอบที่สร้างขึ้นเอง ไม่ได้รันบน production
A66: TC-EM-03 | B66: Backend API (อัตโนมัติ) | C66: refresh token ขอ access token ใหม่ | D66: ล็อกอิน แล้ว POST /api/auth/refresh-token ด้วย refresh token แล้วเอา access token ใหม่ไปเรียก /api/debts | E66: HTTP 200 และ access token ใหม่ใช้เรียก API ได้ | F66: กลาง | G66: อัตโนมัติ | H66: frontend/e2e/tests/account.spec.ts | I66: ผ่าน | J66: 46309 | K66: Playwright (auto, localhost) | L66: ผ่านบน stack ในเครื่อง (localhost: backend + Postgres + Redis + หน้าเว็บ) ด้วยบัญชีทดสอบที่สร้างขึ้นเอง ไม่ได้รันบน production
A67: TC-EM-04 | B67: Backend API (อัตโนมัติ) | C67: เอา refresh token ไปเรียก API ตรง ๆ | D67: GET /api/debts โดยส่ง refresh token เป็น Bearer | E67: ถูกปฏิเสธ (4xx ไม่ใช่ 200) | F67: กลาง | G67: อัตโนมัติ | H67: frontend/e2e/tests/account.spec.ts | I67: ผ่าน | J67: 46309 | K67: Playwright (auto, localhost) | L67: ผ่านบน stack ในเครื่อง (localhost: backend + Postgres + Redis + หน้าเว็บ) ด้วยบัญชีทดสอบที่สร้างขึ้นเอง ไม่ได้รันบน production
A68: TC-EM-05 | B68: Backend API (อัตโนมัติ) | C68: อีเมลถูกแต่รหัสผ่านผิด | D68: POST /api/auth/login ด้วยอีเมลของบัญชีทดสอบและรหัสผ่านที่ตั้งใจให้ผิด | E68: HTTP 401 | F68: สูง | G68: อัตโนมัติ | H68: frontend/e2e/tests/account.spec.ts | I68: ผ่าน | J68: 46309 | K68: Playwright (auto, localhost) | L68: ผ่านทั้งบน production และบน localhost (ไม่ต้องใช้รหัสผ่านจริง)
A69: TC-EM-06 | B69: หน้า Login (UI อัตโนมัติ) | C69: ล็อกอินผ่านหน้าเว็บด้วยบัญชีที่ยืนยันแล้ว แล้วเข้า Home | D69: 1. เปิดเว็บ 2. กรอกอีเมล/รหัสผ่านบัญชีทดสอบ 3. กดเข้าสู่ระบบ | E69: เห็นหน้า Home (ภาพรวมหนี้สิน) และไม่มี request ไป backend ที่ตอบ 4xx/5xx | F69: สูง | G69: อัตโนมัติ | H69: frontend/e2e/tests/account.spec.ts | I69: ผ่าน | J69: 46309 | K69: Playwright (auto, localhost) | L69: ผ่านบน stack ในเครื่อง (localhost: backend + Postgres + Redis + หน้าเว็บ) ด้วยบัญชีทดสอบที่สร้างขึ้นเอง ไม่ได้รันบน production | selector ของหน้า Home ใช้งานได้จริง
A70: TC-EM-07 | B70: หน้า Login (UI อัตโนมัติ) | C70: รีเฟรชหน้า (F5) แล้วยังอยู่ในระบบ | D70: 1. ล็อกอินผ่านหน้าเว็บ 2. กด F5 | E70: ยังเห็นหน้า Home ไม่ถูกเด้งกลับหน้า login | F70: กลาง | G70: อัตโนมัติ | H70: frontend/e2e/tests/account.spec.ts | I70: ผ่าน | J70: 46309 | K70: Playwright (auto, localhost) | L70: ผ่านบน stack ในเครื่อง (localhost: backend + Postgres + Redis + หน้าเว็บ) ด้วยบัญชีทดสอบที่สร้างขึ้นเอง ไม่ได้รันบน production | รีเฟรชแล้วยังอยู่ในระบบ
A71: TC-EM-08 | B71: หน้า Login (UI อัตโนมัติ) | C71: สลับแท็บล่าง (สแกน OCR / งบประมาณ / ตั้งค่า / หน้าหลัก) | D71: 1. ล็อกอิน 2. กดแท็บล่างทีละแท็บ | E71: แต่ละแท็บเปิดได้ และไม่มี request ไป backend ที่ตอบ 4xx/5xx | F71: กลาง | G71: อัตโนมัติ | H71: frontend/e2e/tests/account.spec.ts | I71: ผ่าน | J71: 46309 | K71: Playwright (auto, localhost) | L71: ผ่านบน stack ในเครื่อง (localhost: backend + Postgres + Redis + หน้าเว็บ) ด้วยบัญชีทดสอบที่สร้างขึ้นเอง ไม่ได้รันบน production | สลับ 4 แท็บแล้วไม่มี 4xx/5xx
A72: TC-FT-01 | B72: ฟีเจอร์หลังล็อกอิน (อัตโนมัติ + ทดสอบเอง) | C72: ผู้ใช้ใหม่มีหมวดหมู่เริ่มต้น | D72: GET /api/categories | E72: รายรับ 2 และรายจ่าย 8 หมวด ทุกหมวดมีงบ | F72: สูง | G72: อัตโนมัติ | H72: frontend/e2e/tests/features.spec.ts | I72: ผ่าน | J72: 46309 | K72: Playwright (auto, localhost) | L72: รันบน stack ในเครื่อง (localhost) เพราะสร้าง/แก้/ลบข้อมูล ไม่ได้รันบน production
A73: TC-FT-02 | B73: ฟีเจอร์หลังล็อกอิน (อัตโนมัติ + ทดสอบเอง) | C73: เพิ่ม แก้ไข ลบหมวดหมู่ของตัวเอง | D73: POST/PUT/DELETE /api/categories | E73: ทำได้ครบ และหมวดที่ลบหายจากรายการ | F73: สูง | G73: อัตโนมัติ | H73: frontend/e2e/tests/features.spec.ts | I73: ผ่าน | J73: 46309 | K73: Playwright (auto, localhost) | L73: รันบน stack ในเครื่อง (localhost) เพราะสร้าง/แก้/ลบข้อมูล ไม่ได้รันบน production | เคยตกด้วย 500 (null month) แก้แล้ว commit 4102b66 ยังไม่ได้ยืนยันบน production หลัง deploy
A74: TC-FT-03 | B74: ฟีเจอร์หลังล็อกอิน (อัตโนมัติ + ทดสอบเอง) | C74: สร้างหมวดหมู่โดยไม่ใส่ชื่อ/ประเภท | D74: POST /api/categories ด้วยข้อมูลไม่ครบ | E74: HTTP 400 | F74: กลาง | G74: อัตโนมัติ | H74: frontend/e2e/tests/features.spec.ts | I74: ผ่าน | J74: 46309 | K74: Playwright (auto, localhost) | L74: รันบน stack ในเครื่อง (localhost) เพราะสร้าง/แก้/ลบข้อมูล ไม่ได้รันบน production
A75: TC-FT-04 | B75: ฟีเจอร์หลังล็อกอิน (อัตโนมัติ + ทดสอบเอง) | C75: งบประมาณเดือนปัจจุบันครบทุกหมวด | D75: GET /api/budget และ /budget/overview | E75: ทุกงบเป็นเดือน/ปีปัจจุบัน วงเงินมากกว่า 0 | F75: สูง | G75: อัตโนมัติ | H75: frontend/e2e/tests/features.spec.ts | I75: ผ่าน | J75: 46309 | K75: Playwright (auto, localhost) | L75: รันบน stack ในเครื่อง (localhost) เพราะสร้าง/แก้/ลบข้อมูล ไม่ได้รันบน production
... A104: TC-UF-10 | B104: ฟีเจอร์หลังล็อกอิน (อัตโนมัติ + ทดสอบเอง) | C104: อัปโหลดรูปที่ไม่ใช่สลิปทาง API | D104: POST /api/slips/upload ด้วยรูปข้อความธรรมดา | E104: ผลที่ไม่ใช่ 500 | F104: กลาง | G104: อัตโนมัติ | H104: frontend/e2e/tests/ui-flows.spec.ts | I104: ผ่าน | J104: 46309 | K104: Playwright (auto, localhost) | L104: รันบน stack ในเครื่อง (localhost) สร้าง/แก้/ลบข้อมูลจริง ไม่ได้รันบน production | ใช้ OCR และ MinIO ใน Docker ของเครื่อง
A105: TC-UF-10b | B105: ฟีเจอร์หลังล็อกอิน (อัตโนมัติ + ทดสอบเอง) | C105: อัปโหลดรูปที่ไม่ใช่สลิปผ่านหน้าสแกน | D105: สแกน OCR > แตะอัปโหลด > เลือกจากแกลเลอรี่ > เลือกไฟล์ | E105: แอปส่งรูปไป backend และแจ้งผล | F105: กลาง | G105: อัตโนมัติ | H105: frontend/e2e/tests/ui-flows.spec.ts | I105: ข้าม | L105: รันบน stack ในเครื่อง (localhost) สร้าง/แก้/ลบข้อมูลจริง ไม่ได้รันบน production | ทำเครื่องหมาย fixme: เลือกไฟล์แล้วไม่มี request ออกไป และมี pageerror ทั่วไป ยังไม่ทราบสาเหตุ ต้องทดสอบด้วยมือ
A106: TC-UF-11 | B106: ฟีเจอร์หลังล็อกอิน (อัตโนมัติ + ทดสอบเอง) | C106: บันทึกเงินเดือนในหน้าตั้งค่า | D106: ตั้งค่า > ใส่เงินเดือน > บันทึกการตั้งค่า > ยืนยัน | E106: API เงินเดือนเปลี่ยนตามที่กรอก | F106: กลาง | G106: อัตโนมัติ | H106: frontend/e2e/tests/ui-flows.spec.ts | I106: ผ่าน | J106: 46309 | K106: Playwright (auto, localhost) | L106: รันบน stack ในเครื่อง (localhost) สร้าง/แก้/ลบข้อมูลจริง ไม่ได้รันบน production
A107: TC-UF-12 | B107: ฟีเจอร์หลังล็อกอิน (อัตโนมัติ + ทดสอบเอง) | C107: ออกจากระบบ | D107: ตั้งค่า > ออกจากระบบ > รีเฟรชหน้า | E107: กลับหน้า login และรีเฟรชแล้วยังไม่เข้าระบบ | F107: กลาง | G107: อัตโนมัติ | H107: frontend/e2e/tests/ui-flows.spec.ts | I107: ผ่าน | J107: 46309 | K107: Playwright (auto, localhost) | L107: รันบน stack ในเครื่อง (localhost) สร้าง/แก้/ลบข้อมูลจริง ไม่ได้รันบน production
A108: TC-FT-23 | B108: ฟีเจอร์หลังล็อกอิน (อัตโนมัติ + ทดสอบเอง) | C108: ยอด 'ใช้ไป' ของงบตรงกับธุรกรรมหลังเพิ่ม แก้ไข ลบ | D108: POST แล้ว PUT 100 > 150 แล้ว DELETE ผ่าน API | E108: ยอดใช้ไป = ฐาน+100, ฐาน+150, ฐาน | F108: สูง | G108: อัตโนมัติ | H108: frontend/e2e/tests/features.spec.ts | I108: ผ่าน | J108: 46309 | K108: Playwright (auto, localhost) | L108: รันบน stack ในเครื่อง (localhost) สร้าง/แก้/ลบข้อมูลจริง ไม่ได้รันบน production | เคยพบยอดเพี้ยน (+250 หลังแก้) แก้แล้ว commit b4286b6
A109: BE-UT-11 | B109: Backend Unit Test | C109: สร้างหมวดหมู่ใหม่ ต้องมีเดือน/ปีในงบ | D109: JUnit | E109: ผ่าน | F109: สูง | G109: อัตโนมัติ | H109: backend: CategoryServiceTest.testCreateCategory_BudgetHasMonthAndYear | I109: ผ่าน | J109: 46309 | K109: JUnit (auto)
A110: BE-UT-12 | B110: Backend Unit Test | C110: แก้ธุรกรรมในหมวดเดิม งบเปลี่ยนตามส่วนต่าง | D110: JUnit | E110: ผ่าน | F110: สูง | G110: อัตโนมัติ | H110: backend: TransactionServiceTest.testUpdateTransaction_SameCategory_BudgetChangesByTheDifference | I110: ผ่าน | J110: 46309 | K110: JUnit (auto)
A111: BE-UT-13 | B111: Backend Unit Test | C111: ย้ายธุรกรรมไปหมวดอื่น ยอดย้ายระหว่างงบ | D111: JUnit | E111: ผ่าน | F111: สูง | G111: อัตโนมัติ | H111: backend: TransactionServiceTest.testUpdateTransaction_MovedToAnotherCategory_MovesTheAmountBetweenBudgets | I111: ผ่าน | J111: 46309 | K111: JUnit (auto)
A112: BE-UT-14 | B112: Backend Unit Test | C112: ธุรกรรมที่ตอบกลับมี categoryId | D112: JUnit | E112: ผ่าน | F112: สูง | G112: อัตโนมัติ | H112: backend: TransactionServiceTest.testMapToResponse_IncludesCategoryId | I112: ผ่าน | J112: 46309 | K112: JUnit (auto)
A113: BE-UT-15 | B113: Backend Unit Test | C113: ลบหนี้ ต้องลบประวัติและใบแจ้งยอดก่อนลบหนี้ (กัน foreign key พัง) | D113: JUnit | E113: ผ่าน | F113: สูง | G113: อัตโนมัติ | H113: backend: DebtServiceTest.testDeleteDebt_Success | I113: ผ่าน | J113: 46309 | K113: JUnit (auto) | L113: เคส DebtServiceTest เดิมที่เคยตก (testAddDebt_Success, testDeleteDebt_Success) ผ่านแล้วหลังเพิ่ม mock ที่ขาด
A114: BE-UT-16 | B114: Backend Unit Test | C114: ลบหนี้ การจับคู่ผู้รับเงินที่มีหมวดหมู่ยังอยู่แต่ไม่ชี้หนี้ ส่วนที่ไม่มีหมวดถูกลบ | D114: JUnit | E114: ผ่าน | F114: สูง | G114: อัตโนมัติ | H114: backend: DebtServiceTest.testDeleteDebt_ReceiverMappings_KeepCategoryOnesAndDropTheRest | I114: ผ่าน | J114: 46309 | K114: JUnit (auto) | L114: เคส DebtServiceTest เดิมที่เคยตก (testAddDebt_Success, testDeleteDebt_Success) ผ่านแล้วหลังเพิ่ม mock ที่ขาด
A115: BE-UT-17 | B115: Backend Unit Test | C115: ลบหนี้ที่ไม่พบ ต้องไม่ลบอะไรเลย | D115: JUnit | E115: ผ่าน | F115: สูง | G115: อัตโนมัติ | H115: backend: DebtServiceTest.testDeleteDebt_NotFound_DeletesNothing | I115: ผ่าน | J115: 46309 | K115: JUnit (auto) | L115: เคส DebtServiceTest เดิมที่เคยตก (testAddDebt_Success, testDeleteDebt_Success) ผ่านแล้วหลังเพิ่ม mock ที่ขาด

Sheet Bug ที่พบ
A1: # | B1: อาการ | C1: สาเหตุ | D1: วิธีแก้ | E1: สถานะ | F1: Commit | G1: เทสต์ที่ครอบคลุม
A2: 1 | B2: Google ขึ้น 400 origin_mismatch | C2: origin ของเว็บ (localhost / github.io) ไม่อยู่ใน Authorized JavaScript origins ของ OAuth client | D2: เพิ่ม https://c3b22.github.io (และ localhost:5000) ใน Web client 756271…vpmo ที่ Google Cloud Console | E2: แก้แล้ว | F2: (ตั้งค่า Google Cloud) | G2: TC-GG-02
A3: 2 | B3: 401 Invalid ID token หลังเลือกบัญชี Google | C3: frontend, backend และ Firebase ใช้ Google client ID คนละตัว จึงไม่ตรง audience | D3: ใช้ Web client ID 756271…vpmo ตัวเดียวทั้งหมด และอ่านค่าจาก config / env GOOGLE_CLIENT_ID | E3: แก้แล้ว | F3: 7c888ff | G3: M-G01
A4: 3 | B4: Render deploy ล้ม (Port scan timeout) | C4: แอปบูตช้าเกินบนแพลนฟรี | D4: เติม -XX:TieredStopAtLevel=1 ใน JAVA_TOOL_OPTIONS และตั้ง SPRING_JPA_HIBERNATE_DDL_AUTO=none | E4: แก้แล้ว | F4: ebce29a | G4: TC-API-01
A5: 4 | B5: 500 null value in column month (budget_per_month) | C5: งบเริ่มต้นของผู้ใช้ใหม่ไม่ได้ใส่ month/year | D5: ใส่เดือน/ปีปัจจุบัน (เวลา Asia/Bangkok) ตอนสร้างงบเริ่มต้น | E5: แก้แล้ว | F5: 4c76d69 | G5: BE-UT-05, M-G01
A6: 5 | B6: 401 ทุก request หลังล็อกอินด้วย Google (แอปเด้งกลับ login) | C6: ผู้ใช้ Google ไม่มีรหัสผ่าน แต่ Spring User รับ password เป็น null ไม่ได้ | D6: ใช้สตริงว่างแทน null ใน loadUserByUsername | E6: แก้แล้ว | F6: eac98f0 | G6: BE-UT-04, TC-AUTH-01, M-G04
A7: 6 | B7: 500 เมื่อส่ง idToken ที่ไม่ใช่ JWT หรือไม่ส่งมา | C7: verify(String) throw แล้วถูก catch กลายเป็น 500 | D7: parse token ก่อนและตอบ 401 เมื่อ null/ว่าง/ผิดรูปแบบ | E7: แก้แล้ว | F7: 2959510 | G7: TC-API-06, TC-API-07, TC-API-09, BE-UT-01..03
A8: 7 | B8: ปุ่ม Google เปลี่ยนฟอนต์ไม่ได้ | C8: ปุ่มของ Google render ใน iframe ข้าม origin | D8: วางปุ่มของเราไว้ข้างล่าง และซ้อนปุ่ม Google แบบโปร่งใสไว้ข้างบน | E8: แก้แล้ว | F8: (frontend) | G8: TC-GG-01, M-X05
A9: 8 | B9: สมัครอีเมลแล้วไม่ได้รับรหัส OTP (หน้า ยืนยันอีเมลของคุณ) | C9: RedisConfig สร้าง connection ด้วย host/port เท่านั้น ไม่ส่งรหัสผ่านและ TLS ทั้งที่ตั้งไว้ใน env จึงต่อ Upstash ไม่ได้ (Connection closed prematurely) บันทึก OTP ไม่ได้ | D9: ให้ RedisConfig อ่าน spring.data.redis.password และ ssl.enabled | E9: แก้แล้ว | F9: ba61620 | G9: M-E07
A10: 9 | B10: ยังส่งอีเมล OTP ไม่ได้หลังแก้ Redis (Couldn't connect to host smtp.gmail.com:587) | C10: Render แพลนฟรีบล็อกการเชื่อมต่อ SMTP ขาออก (25/465/587) และเดิมไม่ตั้ง timeout จึงค้างราว 100 วินาที | D10: ใส่ SMTP timeout 10 วินาที (5ed70c2) และเพิ่มการส่งผ่าน Brevo HTTP API (9ac29ad) ต้องตั้ง BREVO_API_KEY + MAIL_FROM บน Render เอง | E10: รอตั้งค่า | F10: 5ed70c2, 9ac29ad | G10: BE-UT-08..10, M-E07
A11: 10 | B11: เพิ่มหมวดหมู่ใหม่ได้ 500 (null value in column month) | C11: CategoryService.createCategory สร้างงบโดยไม่ใส่เดือน/ปี เป็นบั๊กเดียวกับข้อ 4 แต่อยู่อีกจุด เทสต์เดิมตรวจแค่ว่ามีการเรียก createBudget จึงไม่เห็น | D11: ใส่เดือน/ปีปัจจุบัน (Asia/Bangkok) และเพิ่ม unit test ที่ตรวจค่าจริง | E11: แก้แล้ว (push แล้ว) | F11: 4102b66 | G11: TC-FT-02, CategoryServiceTest
A12: 11 | B12: ลบหนี้ที่เคยจ่ายแล้วได้ 500 (foreign key กับ debt_transactions) | C12: ตาราง debt_transactions อ้างอิง debt แต่โค้ดลบ debt โดยไม่จัดการประวัติ | D12: ลบข้อมูลที่ผูกกับหนี้ก่อน (ประวัติการจ่าย ใบแจ้งยอด) และเอาหนี้ออกจากการจับคู่ผู้รับเงิน ทั้งหมดใน transaction เดียว แล้วค่อยลบหนี้ ลบแล้วประวัติหายตาม | E12: แก้แล้ว (push แล้ว) | F12: c1744f9 | G12: TC-FT-21, BE-UT-15, BE-UT-16, BE-UT-17
... A22: 21 | B22: unit test เดิมของ backend ตก 21 ข้อ (จาก 183 ข้อ) | C22: ตกมาก่อนการแก้ทั้งหมด (ยืนยันบน commit 993a11b ตก 23 ข้อชุดเดียวกัน) สาเหตุหลักคือ Spring context โหลดไม่ได้ในการทดสอบ (ต้องใช้ JWT_SECRET และบริการภายนอก) ควบคุมเทสต์ที่ mock ไม่ครบ และเทสต์ที่ไม่ตรงกับโค้ดปัจจุบัน | D22: ยังไม่ได้แก้ ควรให้ CI รัน ./gradlew test และแก้ทีละกลุ่ม (เริ่มจากตั้งค่า test profile ให้ context โหลดได้) | E22: ยังไม่แก้ | F22: - | G22: BE-UT-07
